kubeasy_builder/__init__.py
kubeasy_builder/build.py
kubeasy_sdk/__init__.py
kubeasy_sdk/container.py
kubeasy_sdk/deployment.py
kubeasy_sdk/ingress.py
kubeasy_sdk/service.py
kubeasy_sdk/volume.py
kubeasy_server/__init__.py
kubeasy_server/run.py
kubeasy_py-0.1.15.dist-info/LICENSE.txt
kubeasy_py-0.1.15.dist-info/METADATA
kubeasy_py-0.1.15.dist-info/WHEEL
kubeasy_py-0.1.15.dist-info/top_level.txt
kubeasy_py-0.1.15.dist-info/RECORD
