Metadata-Version: 2.1
Name: kubeasy-py
Version: 0.1.15
Summary: Kubernetes made easy!
Home-page: https://github.com/dylanturn/kubeasy
Author: Dylan Turnbull
Author-email: dylanturn@gmail.com
License: UNKNOWN
Platform: UNKNOWN
Classifier: Programming Language :: Python :: 3
Classifier: License :: OSI Approved :: Apache Software License
Classifier: Operating System :: OS Independent
Requires-Python: >=3.8
